kmtools/__init__.py
kmtools/db_tools/__init__.py
kmtools/db_tools/_db_tools.py
kmtools/db_tools/_print_sql.py
kmtools/db_tools/g2d.py
kmtools/df_tools/__init__.py
kmtools/df_tools/_data_analysis.py
kmtools/df_tools/_df_tools.py
kmtools/df_tools/_loaders.py
kmtools/df_tools/_pandas.py
kmtools/df_tools/_parquet.py
kmtools/df_tools/stats.py
kmtools/ml_tools/__init__.py
kmtools/ml_tools/gridsearch.py
kmtools/py_tools/__init__.py
kmtools/py_tools/basics.py
kmtools/py_tools/deprecation.py
kmtools/py_tools/itertools.py
kmtools/py_tools/logging.py
kmtools/py_tools/serialization.py
kmtools/py_tools/test_tools.py
kmtools/sequence_tools/__init__.py
kmtools/sequence_tools/alignment_tools.py
kmtools/sequence_tools/blast.py
kmtools/sequence_tools/codons_info.py
kmtools/sequence_tools/dna_util.py
kmtools/sequence_tools/fasta_tools.py
kmtools/sequence_tools/fastq_tools.py
kmtools/sequence_tools/psipred.py
kmtools/sequence_tools/sequence_tools.py
kmtools/sequence_tools/slims.py
kmtools/sequence_tools/vcf.py
kmtools/sequence_tools/support/elms_classes.csv
kmtools/sequence_tools/support/elms_pepx.csv
kmtools/structure_tools/__init__.py
kmtools/structure_tools/constants.py
kmtools/structure_tools/elaspic_legacy.py
kmtools/structure_tools/exc.py
kmtools/structure_tools/interaction.py
kmtools/structure_tools/modeller.py
kmtools/structure_tools/sequence.py
kmtools/structure_tools/sifts.py
kmtools/structure_tools/structure_parser.py
kmtools/structure_tools/structure_parser_legacy.py
kmtools/structure_tools/data/residue_mapping_to_canonical.json
kmtools/structure_tools/data/standard_sasa.txt
kmtools/system_tools/__init__.py
kmtools/system_tools/_compression.py
kmtools/system_tools/_locking.py
kmtools/system_tools/_pathlib.py
kmtools/system_tools/_remote.py
kmtools/system_tools/_retrying.py
kmtools/system_tools/_subprocess.py
kmtools/system_tools/exc.py
kmtools-0.0.27.dist-info/METADATA
kmtools-0.0.27.dist-info/RECORD
kmtools-0.0.27.dist-info/WHEEL
kmtools-0.0.27.dist-info/top_level.txt
