Metadata-Version: 2.1
Name: kmtools
Version: 0.0.27
Summary: Bits of reusable code to make our lives easier.
Home-page: https://gitlab.com/kimlab/kmtools
Author: kimlab.org
Author-email: alex.strokach@utoronto.ca
License: MIT
Platform: UNKNOWN
Classifier: License :: OSI Approved :: MIT License
Classifier: Programming Language :: Python :: 3 :: Only
Classifier: Topic :: Scientific/Engineering :: Bio-Informatics
